np_rw_buffer/__init__.py
np_rw_buffer/__meta__.py
np_rw_buffer/_circular_indexes.c
np_rw_buffer/_circular_indexes.cp313-win_amd64.pyd
np_rw_buffer/audio_buffer.py
np_rw_buffer/buffer.py
np_rw_buffer/circular_indexes.py
np_rw_buffer/manager.py
np_rw_buffer/utils.py
np_rw_buffer-1.2.0.dist-info/licenses/LICENSE
np_rw_buffer-1.2.0.dist-info/METADATA
np_rw_buffer-1.2.0.dist-info/WHEEL
np_rw_buffer-1.2.0.dist-info/top_level.txt
np_rw_buffer-1.2.0.dist-info/RECORD
