Metadata-Version: 2.4
Name: np_rw_buffer
Version: 1.2.0
Summary: Library to help store audio data in a circular buffer
Home-page: https://github.com/justengel/np_rw_buffer
Download-URL: https://github.com/justengel/np_rw_buffer/archive/v1.2.0.tar.gz
Author: Justin Engel
Author-email: Justin Engel <jtengel08@gmail.com>
License: MIT License
Project-URL: Repository, https://github.com/justengel/np_rw_buffer
Keywords: read,write,ring,circular,buffer
Classifier: Development Status :: 4 - Beta
Classifier: Intended Audience :: Developers
Classifier: Topic :: Software Development :: Libraries :: Python Modules
Classifier: Topic :: Multimedia :: Sound/Audio
Classifier: License :: OSI Approved :: MIT License
Classifier: Programming Language :: Python :: 3
Classifier: Programming Language :: Python :: 3.13
Classifier: Operating System :: OS Independent
Requires-Python: >=3.13
License-File: LICENSE
Requires-Dist: numpy>=1.26.0
Dynamic: author
Dynamic: download-url
Dynamic: home-page
Dynamic: license-file
